{
    "Ar36": {
        "error": 0.0004527703049024569,
        "error_type": "SEM",
        "filter_outliers_dict": {
            "filter_outliers": true,
            "iterations": 1,
            "std_devs": 3,
            "use_iqr_filtering": false,
            "use_standard_deviation_filtering": false
        },
        "fit": "linear",
        "fn": 339,
        "include_baseline_error": true,
        "n": 340,
        "outlier_excluded": [
            55
        ],
        "reviewed": true,
        "user_excluded": [],
        "value": 0.08691906782287515
    },
    "Ar37": {
        "error": 0.017465333305150654,
        "error_type": "SEM",
        "filter_outliers_dict": {
            "filter_outliers": true,
            "iterations": 1,
            "std_devs": 3,
            "use_iqr_filtering": false,
            "use_standard_deviation_filtering": false
        },
        "fit": "linear",
        "fn": 338,
        "include_baseline_error": true,
        "n": 340,
        "outlier_excluded": [
            157,
            198
        ],
        "reviewed": true,
        "user_excluded": [],
        "value": 24.356069208518733
    },
    "Ar38": {
        "error": 0.005456065349306623,
        "error_type": "SEM",
        "filter_outliers_dict": {
            "filter_outliers": true,
            "iterations": 1,
            "std_devs": 3,
            "use_iqr_filtering": false,
            "use_standard_deviation_filtering": false
        },
        "fit": "linear",
        "fn": 339,
        "include_baseline_error": true,
        "n": 340,
        "outlier_excluded": [
            17
        ],
        "reviewed": true,
        "user_excluded": [],
        "value": 0.3542055001312422
    },
    "Ar39": {
        "error": 0.008932644042814849,
        "error_type": "SEM",
        "filter_outliers_dict": {
            "filter_outliers": true,
            "iterations": 1,
            "std_devs": 3,
            "use_iqr_filtering": false,
            "use_standard_deviation_filtering": false
        },
        "fit": "linear",
        "fn": 340,
        "include_baseline_error": true,
        "n": 340,
        "outlier_excluded": [],
        "reviewed": true,
        "user_excluded": [],
        "value": 18.04223880161981
    },
    "Ar40": {
        "error": 0.03488385661373262,
        "error_type": "SEM",
        "filter_outliers_dict": {
            "filter_outliers": true,
            "iterations": 1,
            "std_devs": 3,
            "use_iqr_filtering": false,
            "use_standard_deviation_filtering": false
        },
        "fit": "parabolic",
        "fn": 339,
        "include_baseline_error": true,
        "n": 340,
        "outlier_excluded": [
            179
        ],
        "reviewed": true,
        "user_excluded": [],
        "value": 97.3190762811258
    }
}